parldl/__init__.py
parldl/__main__.py
parldl-0.2.0.dist-info/entry_points.txt
parldl-0.2.0.dist-info/WHEEL
parldl-0.2.0.dist-info/METADATA
parldl-0.2.0.dist-info/LICENSE
parldl-0.2.0.dist-info/RECORD
