Metadata-Version: 2.1
Name: parldl
Version: 0.2.0
Summary: Download files parallely from a list of URLs in a file
Home-page: https://github.com/aqdasak/parldl
License: MIT
Keywords: python,parallel,download,urls
Author: Aqdas Ahmad Khan
Author-email: aqdasak@gmail.com
Requires-Python: >=3.10,<4.0
Classifier: License :: OSI Approved :: MIT License
Classifier: Programming Language :: Python :: 3
Classifier: Programming Language :: Python :: 3.10
Classifier: Programming Language :: Python :: 3.11
Requires-Dist: click (>=8.1.7,<9.0.0)
Requires-Dist: requests (>=2.32.3,<3.0.0)
Project-URL: Repository, https://github.com/aqdasak/parldl
